README.md
_version.py
setup.py
obflib/__init__.py
obflib/cli.py
obflib/message_handler.py
obflib/py.typed
obflib/reader.py
obflib/verifier.py
obflib.egg-info/PKG-INFO
obflib.egg-info/SOURCES.txt
obflib.egg-info/dependency_links.txt
obflib.egg-info/entry_points.txt
obflib.egg-info/requires.txt
obflib.egg-info/top_level.txt
openbuildfile/__init__.py
openbuildfile/examples/__init__.py
openbuildfile/examples/invalid.obf
openbuildfile/examples/standard.obf
openbuildfile/examples/standard/buildProcessors/bob/build.lua
openbuildfile/examples/standard/buildProcessors/bob/old_build.lua
openbuildfile/schemas/__init__.py
openbuildfile/schemas/v1/buildInfo.json
openbuildfile/schemas/v1/buildProcessors.json
openbuildfile/schemas/v1/machineCapabilities.json
openbuildfile/schemas/v1/manifest.json
openbuildfile/schemas/v1/module.json