Metadata-Version: 2.1
Name: obflib
Version: 0.3.4
Summary: Python library for verifying, reading and manipulating OBF files for use in metal 3D printers from Freemelt AB
Home-page: https://gitlab.com/freemelt/openmelt/obflib-python
Author: Freemelt AB
Author-email: opensource@freemelt.com
Maintainer: Freemelt AB
Maintainer-email: opensource@freemelt.com
License: apache-2.0
Keywords: obf openbuildfile freemelt
Platform: UNKNOWN
Classifier: Development Status :: 3 - Alpha
Classifier: Intended Audience :: Developers
Classifier: Programming Language :: Python :: 3
Classifier: License :: OSI Approved :: Apache Software License
Classifier: Operating System :: OS Independent
Requires-Python: >=3.7
